topping/__init__.py
topping/core.py
topping/exporter.py
topping/field.py
topping/model.py
topping-0.1.1.dist-info/METADATA
topping-0.1.1.dist-info/WHEEL
topping-0.1.1.dist-info/LICENSE.md
topping-0.1.1.dist-info/RECORD
