Metadata-Version: 2.1
Name: topping
Version: 0.1.1
Summary: Topping is a Python library for tracking function data.
Author: jenz
Author-email: 2025.jenz@gmail.com
Requires-Python: >=3.8,<4.0
Classifier: Programming Language :: Python :: 3
Classifier: Programming Language :: Python :: 3.8
Classifier: Programming Language :: Python :: 3.9
Classifier: Programming Language :: Python :: 3.10
Classifier: Programming Language :: Python :: 3.11
Requires-Dist: rich (>=13.2.0,<14.0.0)
